clap/__init__.py
clap/arguments.py
clap/commands.py
clap/converter.py
clap/errors.py
clap/groups.py
clap/help.py
clap/lexer.py
clap/metadata.py
clap/options.py
clap/parser.py
clap/py.typed
clap/utils.py
docs/source/conf.py
scripts/has_docstrings.py
tests/test_parser.py
ndg.clap-0.1.4.dist-info/LICENSE
ndg.clap-0.1.4.dist-info/METADATA
ndg.clap-0.1.4.dist-info/WHEEL
ndg.clap-0.1.4.dist-info/top_level.txt
ndg.clap-0.1.4.dist-info/RECORD
